[
    {
        "create_time": "2016-11-19 07:39:32.546652",
        "datasets": [
            {
                "dataset_id": "17919440",
                "extension": "bam",
                "file_size": 302497254,
                "name": "Sugar fed_2",
                "param_name": "bamfiles"
            },
            {
                "dataset_id": "17919440",
                "extension": "bam",
                "file_size": 302497254,
                "name": "Sugar fed_2",
                "param_name": "bamfiles1"
            },
            {
                "dataset_id": "17919130",
                "extension": "bam",
                "file_size": 242529627,
                "name": "Blood-fed adult females_2",
                "param_name": "bamfiles2"
            },
            {
                "dataset_id": "17919136",
                "extension": "bam",
                "file_size": 176190912,
                "name": "Adult males_2",
                "param_name": "bamfiles3"
            },
            {
                "dataset_id": "17919443",
                "extension": "bam",
                "file_size": 232334559,
                "name": "Pupae_2",
                "param_name": "bamfiles4"
            },
            {
                "dataset_id": "17919446",
                "extension": "bam",
                "file_size": 241379484,
                "name": "Larvae_2",
                "param_name": "bamfiles5"
            },
            {
                "dataset_id": "17919127",
                "extension": "bam",
                "file_size": 159082984,
                "name": "0-24 embryo_2",
                "param_name": "bamfiles6"
            },
            {
                "dataset_id": "17893289",
                "extension": "bam",
                "file_size": 190463735,
                "name": "Sugar fed",
                "param_name": "bamfiles7"
            },
            {
                "dataset_id": "17891636",
                "extension": "bam",
                "file_size": 105735531,
                "name": "Blood-fed adult females",
                "param_name": "bamfiles8"
            },
            {
                "dataset_id": "17908143",
                "extension": "bam",
                "file_size": 33959331,
                "name": "Adult females",
                "param_name": "bamfiles9"
            },
            {
                "dataset_id": "17897799",
                "extension": "bam",
                "file_size": 104612958,
                "name": "Adult males",
                "param_name": "bamfiles10"
            },
            {
                "dataset_id": "17903240",
                "extension": "bam",
                "file_size": 115999925,
                "name": "Pupae",
                "param_name": "bamfiles11"
            },
            {
                "dataset_id": "17893275",
                "extension": "bam",
                "file_size": 122309874,
                "name": "Larvae",
                "param_name": "bamfiles12"
            },
            {
                "dataset_id": "17890405",
                "extension": "bam",
                "file_size": 78303267,
                "name": "0-24 embryo",
                "param_name": "bamfiles13"
            }
        ],
        "dependencies": null,
        "destination_id": "slurm_multi",
        "destination_params": {
            "nativeSpecification": "--time=36:00:00 --nodes=1 --ntasks=6 --partition=multi"
        },
        "exit_code": null,
        "handler": "main_w4_handler2",
        "history_id": 2896568,
        "id": 14383194,
        "imported": false,
        "info": "This job was terminated because it ran longer than the maximum allowed job run time.\nPlease click the bug icon to report this problem if you need help.",
        "job_runner_external_id": "8588964",
        "job_runner_name": "slurm",
        "library_folder_id": null,
        "metrics": {},
        "object_store_id": "corral-repl",
        "param_filename": null,
        "parameters": {
            "__job_resource": "{\"__current_case__\": 0, \"__job_resource__select\": \"no\"}",
            "advancedOpt": "{\"showAdvancedOpt\": \"no\", \"__current_case__\": 0}",
            "bamfiles": "{\"values\": [{\"src\": \"hdca\", \"id\": \"ff366716096a8a6a\"}]}",
            "chromInfo": "\"/galaxy-repl/localdata/chrom/?.len\"",
            "dbkey": "\"?\"",
            "mode": "{\"binSize\": \"10000\", \"distanceBetweenBins\": \"0\", \"__current_case__\": 0, \"modeOpt\": \"bins\"}",
            "outRawCounts": "\"false\"",
            "region": "\"\""
        },
        "runner_name": null,
        "session_id": 34346925,
        "state": "error",
        "tool_id": "toolshed.g2.bx.psu.edu/repos/bgruening/deeptools_multi_bam_summary/deeptools_multi_bam_summary/2.3.6.0",
        "tool_version": "2.3.6.0",
        "traceback": null,
        "update_time": "2016-11-20 19:43:19.332506",
        "user_id": 91783
    },
    {
        "create_time": "2017-01-26 17:05:57.933367",
        "datasets": [
            {
                "dataset_id": "18614112",
                "extension": "bam",
                "file_size": 320835882,
                "name": "Reheader S1L1",
                "param_name": "bamfiles"
            },
            {
                "dataset_id": "18614112",
                "extension": "bam",
                "file_size": 320835882,
                "name": "Reheader S1L1",
                "param_name": "bamfiles1"
            },
            {
                "dataset_id": "18614255",
                "extension": "bam",
                "file_size": 204834168,
                "name": "Reheader S1L2",
                "param_name": "bamfiles2"
            },
            {
                "dataset_id": "18614259",
                "extension": "bam",
                "file_size": 204450599,
                "name": "Reheader S1L3",
                "param_name": "bamfiles3"
            },
            {
                "dataset_id": "18614261",
                "extension": "bam",
                "file_size": 192517637,
                "name": "Reheader S1L4",
                "param_name": "bamfiles4"
            },
            {
                "dataset_id": "18614266",
                "extension": "bam",
                "file_size": 294844723,
                "name": "Reheader S2L1",
                "param_name": "bamfiles5"
            },
            {
                "dataset_id": "18614270",
                "extension": "bam",
                "file_size": 290844807,
                "name": "Reheader S2L2",
                "param_name": "bamfiles6"
            },
            {
                "dataset_id": "18614276",
                "extension": "bam",
                "file_size": 284803481,
                "name": "Reheader S2L3",
                "param_name": "bamfiles7"
            },
            {
                "dataset_id": "18614277",
                "extension": "bam",
                "file_size": 276206424,
                "name": "Reheader S2L4",
                "param_name": "bamfiles8"
            }
        ],
        "dependencies": [
            {
                "cacheable": true,
                "dependency_type": "conda",
                "environment_path": "/galaxy-repl/main/jobdir/014/880/14880286/conda-env",
                "exact": true,
                "model_class": "CondaDependency",
                "name": "python",
                "version": "2.7.10"
            },
            {
                "cacheable": true,
                "dependency_type": "conda",
                "environment_path": "/galaxy-repl/main/jobdir/014/880/14880286/conda-env",
                "exact": true,
                "model_class": "CondaDependency",
                "name": "deepTools",
                "version": "2.3.6"
            }
        ],
        "destination_id": "slurm_multi",
        "destination_params": {
            "nativeSpecification": "--time=36:00:00 --nodes=1 --ntasks=6 --partition=multi"
        },
        "exit_code": null,
        "handler": "main_w4_handler2",
        "history_id": 2968105,
        "id": 14880286,
        "imported": false,
        "info": "This job was terminated because it ran longer than the maximum allowed job run time.\nPlease click the bug icon to report this problem if you need help.",
        "job_runner_external_id": "9039845",
        "job_runner_name": "slurm",
        "library_folder_id": null,
        "metrics": {},
        "object_store_id": "corral-repl",
        "param_filename": null,
        "parameters": {
            "__job_resource": "{\"__current_case__\": 0, \"__job_resource__select\": \"no\"}",
            "advancedOpt": "{\"showAdvancedOpt\": \"no\", \"__current_case__\": 0}",
            "bamfiles": "{\"values\": [{\"src\": \"hda\", \"id\": 28095307}, {\"src\": \"hda\", \"id\": 28095451}, {\"src\": \"hda\", \"id\": 28095455}, {\"src\": \"hda\", \"id\": 28095457}, {\"src\": \"hda\", \"id\": 28095462}, {\"src\": \"hda\", \"id\": 28095466}, {\"src\": \"hda\", \"id\": 28095472}, {\"src\": \"hda\", \"id\": 28095473}]}",
            "chromInfo": "\"/galaxy-repl/localdata/chrom/?.len\"",
            "dbkey": "\"?\"",
            "mode": "{\"binSize\": \"10000\", \"distanceBetweenBins\": \"0\", \"__current_case__\": 0, \"modeOpt\": \"bins\"}",
            "outRawCounts": "\"false\"",
            "region": "\"\""
        },
        "runner_name": null,
        "session_id": 35170344,
        "state": "error",
        "tool_id": "toolshed.g2.bx.psu.edu/repos/bgruening/deeptools_multi_bam_summary/deeptools_multi_bam_summary/2.3.6.0",
        "tool_version": "2.3.6.0",
        "traceback": null,
        "update_time": "2017-01-28 05:19:11.058680",
        "user_id": 17286
    },
    {
        "create_time": "2017-01-31 15:49:27.991618",
        "datasets": [
            {
                "dataset_id": "18663972",
                "extension": "bam",
                "file_size": 188542196,
                "name": "Slice S1L1",
                "param_name": "bamfiles"
            },
            {
                "dataset_id": "18663972",
                "extension": "bam",
                "file_size": 188542196,
                "name": "Slice S1L1",
                "param_name": "bamfiles1"
            },
            {
                "dataset_id": "18664284",
                "extension": "bam",
                "file_size": 182317876,
                "name": "Slice S1L2",
                "param_name": "bamfiles2"
            },
            {
                "dataset_id": "18664285",
                "extension": "bam",
                "file_size": 181856140,
                "name": "Slice S1L3",
                "param_name": "bamfiles3"
            },
            {
                "dataset_id": "18664287",
                "extension": "bam",
                "file_size": 171154965,
                "name": "Slice S1L4",
                "param_name": "bamfiles4"
            },
            {
                "dataset_id": "18664288",
                "extension": "bam",
                "file_size": 263204252,
                "name": "Slice S2L1",
                "param_name": "bamfiles5"
            },
            {
                "dataset_id": "18664289",
                "extension": "bam",
                "file_size": 259596975,
                "name": "Slice S2L2",
                "param_name": "bamfiles6"
            },
            {
                "dataset_id": "18664290",
                "extension": "bam",
                "file_size": 254089624,
                "name": "Slice S2L3",
                "param_name": "bamfiles7"
            },
            {
                "dataset_id": "18664291",
                "extension": "bam",
                "file_size": 246250022,
                "name": "Slice S2L4",
                "param_name": "bamfiles8"
            }
        ],
        "dependencies": [
            {
                "cacheable": true,
                "dependency_type": "conda",
                "environment_path": "/galaxy-repl/main/jobdir/014/915/14915996/conda-env",
                "exact": true,
                "model_class": "CondaDependency",
                "name": "python",
                "version": "2.7.10"
            },
            {
                "cacheable": true,
                "dependency_type": "conda",
                "environment_path": "/galaxy-repl/main/jobdir/014/915/14915996/conda-env",
                "exact": true,
                "model_class": "CondaDependency",
                "name": "deepTools",
                "version": "2.3.6"
            }
        ],
        "destination_id": "slurm_multi",
        "destination_params": {
            "nativeSpecification": "--time=36:00:00 --nodes=1 --ntasks=6 --partition=multi"
        },
        "exit_code": null,
        "handler": "main_w3_handler2",
        "history_id": 2975299,
        "id": 14915996,
        "imported": false,
        "info": "This job was terminated because it ran longer than the maximum allowed job run time.\nPlease click the bug icon to report this problem if you need help.",
        "job_runner_external_id": "9093757",
        "job_runner_name": "slurm",
        "library_folder_id": null,
        "metrics": {},
        "object_store_id": "corral-repl",
        "param_filename": null,
        "parameters": {
            "__job_resource": "{\"__current_case__\": 0, \"__job_resource__select\": \"no\"}",
            "advancedOpt": "{\"showAdvancedOpt\": \"no\", \"__current_case__\": 0}",
            "bamfiles": "{\"values\": [{\"src\": \"hda\", \"id\": 28153829}, {\"src\": \"hda\", \"id\": 28154156}, {\"src\": \"hda\", \"id\": 28154157}, {\"src\": \"hda\", \"id\": 28154159}, {\"src\": \"hda\", \"id\": 28154160}, {\"src\": \"hda\", \"id\": 28154161}, {\"src\": \"hda\", \"id\": 28154162}, {\"src\": \"hda\", \"id\": 28154163}]}",
            "chromInfo": "\"/galaxy-repl/localdata/chrom/?.len\"",
            "dbkey": "\"?\"",
            "mode": "{\"binSize\": \"10000\", \"distanceBetweenBins\": \"0\", \"__current_case__\": 0, \"modeOpt\": \"bins\"}",
            "outRawCounts": "\"false\"",
            "region": "\"\""
        },
        "runner_name": null,
        "session_id": 35170344,
        "state": "error",
        "tool_id": "toolshed.g2.bx.psu.edu/repos/bgruening/deeptools_multi_bam_summary/deeptools_multi_bam_summary/2.3.6.0",
        "tool_version": "2.3.6.0",
        "traceback": null,
        "update_time": "2017-02-04 09:40:26.859558",
        "user_id": 17286
    },
    {
        "create_time": "2017-01-31 21:57:00.732260",
        "datasets": [
            {
                "dataset_id": "18663972",
                "extension": "bam",
                "file_size": 188542196,
                "name": "Slice S1L1",
                "param_name": "bamfiles"
            },
            {
                "dataset_id": "18663972",
                "extension": "bam",
                "file_size": 188542196,
                "name": "Slice S1L1",
                "param_name": "bamfiles1"
            },
            {
                "dataset_id": "18664284",
                "extension": "bam",
                "file_size": 182317876,
                "name": "Slice S1L2",
                "param_name": "bamfiles2"
            },
            {
                "dataset_id": "18664285",
                "extension": "bam",
                "file_size": 181856140,
                "name": "Slice S1L3",
                "param_name": "bamfiles3"
            },
            {
                "dataset_id": "18664287",
                "extension": "bam",
                "file_size": 171154965,
                "name": "Slice S1L4",
                "param_name": "bamfiles4"
            },
            {
                "dataset_id": "18664288",
                "extension": "bam",
                "file_size": 263204252,
                "name": "Slice S2L1",
                "param_name": "bamfiles5"
            },
            {
                "dataset_id": "18664289",
                "extension": "bam",
                "file_size": 259596975,
                "name": "Slice S2L2",
                "param_name": "bamfiles6"
            },
            {
                "dataset_id": "18664290",
                "extension": "bam",
                "file_size": 254089624,
                "name": "Slice S2L3",
                "param_name": "bamfiles7"
            },
            {
                "dataset_id": "18664291",
                "extension": "bam",
                "file_size": 246250022,
                "name": "Slice S2L4",
                "param_name": "bamfiles8"
            }
        ],
        "dependencies": [
            {
                "cacheable": true,
                "dependency_type": "conda",
                "environment_path": "/galaxy-repl/main/jobdir/014/918/14918301/conda-env",
                "exact": true,
                "model_class": "CondaDependency",
                "name": "python",
                "version": "2.7.10"
            },
            {
                "cacheable": true,
                "dependency_type": "conda",
                "environment_path": "/galaxy-repl/main/jobdir/014/918/14918301/conda-env",
                "exact": true,
                "model_class": "CondaDependency",
                "name": "deepTools",
                "version": "2.3.6"
            }
        ],
        "destination_id": "slurm_multi",
        "destination_params": {
            "nativeSpecification": "--time=36:00:00 --nodes=1 --ntasks=6 --partition=multi"
        },
        "exit_code": null,
        "handler": "main_w3_handler2",
        "history_id": 2976852,
        "id": 14918301,
        "imported": false,
        "info": "This job was terminated because it ran longer than the maximum allowed job run time.\nPlease click the bug icon to report this problem if you need help.",
        "job_runner_external_id": "9113310",
        "job_runner_name": "slurm",
        "library_folder_id": null,
        "metrics": {},
        "object_store_id": "corral-repl",
        "param_filename": null,
        "parameters": {
            "__job_resource": "{\"__current_case__\": 0, \"__job_resource__select\": \"no\"}",
            "advancedOpt": "{\"showAdvancedOpt\": \"no\", \"__current_case__\": 0}",
            "bamfiles": "{\"values\": [{\"src\": \"hda\", \"id\": 28158526}, {\"src\": \"hda\", \"id\": 28158527}, {\"src\": \"hda\", \"id\": 28158529}, {\"src\": \"hda\", \"id\": 28158530}, {\"src\": \"hda\", \"id\": 28158531}, {\"src\": \"hda\", \"id\": 28158533}, {\"src\": \"hda\", \"id\": 28158534}, {\"src\": \"hda\", \"id\": 28158536}]}",
            "chromInfo": "\"/galaxy-repl/localdata/chrom/?.len\"",
            "dbkey": "\"?\"",
            "mode": "{\"binSize\": \"10000\", \"distanceBetweenBins\": \"0\", \"__current_case__\": 0, \"modeOpt\": \"bins\"}",
            "outRawCounts": "\"false\"",
            "region": "\"chr1L\""
        },
        "runner_name": null,
        "session_id": 35170344,
        "state": "error",
        "tool_id": "toolshed.g2.bx.psu.edu/repos/bgruening/deeptools_multi_bam_summary/deeptools_multi_bam_summary/2.3.6.0",
        "tool_version": "2.3.6.0",
        "traceback": null,
        "update_time": "2017-02-07 09:49:20.480378",
        "user_id": 17286
    },
    {
        "create_time": "2017-02-07 18:29:01.787571",
        "datasets": [
            {
                "dataset_id": "18714174",
                "extension": "bam",
                "file_size": 624723735,
                "name": "AK47_TGACCA_L001",
                "param_name": "bamfiles"
            },
            {
                "dataset_id": "18714174",
                "extension": "bam",
                "file_size": 624723735,
                "name": "AK47_TGACCA_L001",
                "param_name": "bamfiles1"
            },
            {
                "dataset_id": "18714282",
                "extension": "bam",
                "file_size": 613505804,
                "name": "AfghanKush_CGATGT_L001",
                "param_name": "bamfiles2"
            },
            {
                "dataset_id": "18714333",
                "extension": "bam",
                "file_size": 192940192,
                "name": "Afgooey_ACTTGA_L001",
                "param_name": "bamfiles3"
            },
            {
                "dataset_id": "18714564",
                "extension": "bam",
                "file_size": 489945762,
                "name": "AlaskanIce_TTAGGC_L001",
                "param_name": "bamfiles4"
            },
            {
                "dataset_id": "18714584",
                "extension": "bam",
                "file_size": 313137453,
                "name": "ArjanUltraHaze2_GCCAAT_L001",
                "param_name": "bamfiles5"
            },
            {
                "dataset_id": "18714646",
                "extension": "bam",
                "file_size": 243532641,
                "name": "AustralianBastard_TTAGGC_L001",
                "param_name": "bamfiles6"
            },
            {
                "dataset_id": "18714734",
                "extension": "bam",
                "file_size": 243532643,
                "name": "BlueBerryCheeseCake18_ACAGTG_L001",
                "param_name": "bamfiles7"
            },
            {
                "dataset_id": "18715697",
                "extension": "bam",
                "file_size": 413003853,
                "name": "BlueBerryCheeseCakeBC2Fem_TAGCTT_L001",
                "param_name": "bamfiles8"
            },
            {
                "dataset_id": "18715705",
                "extension": "bam",
                "file_size": 414003695,
                "name": "BlueBerryEssense_CAGATC_L001",
                "param_name": "bamfiles9"
            },
            {
                "dataset_id": "18715759",
                "extension": "bam",
                "file_size": 334014135,
                "name": "BlueDreamSCC_CAGATC_L001",
                "param_name": "bamfiles10"
            },
            {
                "dataset_id": "18715798",
                "extension": "bam",
                "file_size": 692881481,
                "name": "Breakthrough_CTTGTA_L001",
                "param_name": "bamfiles11"
            },
            {
                "dataset_id": "18716513",
                "extension": "bam",
                "file_size": 275109667,
                "name": "C4XCanatsuSCC_Pooled_L001",
                "param_name": "bamfiles12"
            },
            {
                "dataset_id": "18716520",
                "extension": "bam",
                "file_size": 360911840,
                "name": "CBDMangoHaze_CAGATC_L001",
                "param_name": "bamfiles13"
            },
            {
                "dataset_id": "18716550",
                "extension": "bam",
                "file_size": 223969320,
                "name": "CanaTsuSCC_GATCAG_L001",
                "param_name": "bamfiles14"
            },
            {
                "dataset_id": "18716559",
                "extension": "bam",
                "file_size": 391115675,
                "name": "CaseyJones_ACAGTG_L001",
                "param_name": "bamfiles15"
            },
            {
                "dataset_id": "18716575",
                "extension": "bam",
                "file_size": 45295398,
                "name": "CheeseGHS_AGTTCC_L001",
                "param_name": "bamfiles16"
            },
            {
                "dataset_id": "18716618",
                "extension": "bam",
                "file_size": 29786038,
                "name": "ChemDawg91_GCCAAT_L001",
                "param_name": "bamfiles17"
            },
            {
                "dataset_id": "18716625",
                "extension": "bam",
                "file_size": 331182787,
                "name": "ChemDawg_ATCACG_L001",
                "param_name": "bamfiles18"
            },
            {
                "dataset_id": "18717240",
                "extension": "bam",
                "file_size": 557341204,
                "name": "ChemDog18cycles_ATCACG_L001",
                "param_name": "bamfiles19"
            },
            {
                "dataset_id": "18717249",
                "extension": "bam",
                "file_size": 379850451,
                "name": "ChemDog_TTAGGC_L001",
                "param_name": "bamfiles20"
            },
            {
                "dataset_id": "18717279",
                "extension": "bam",
                "file_size": 338227868,
                "name": "ChemdogXCherryPieSCC_TTAGGC_L001",
                "param_name": "bamfiles21"
            },
            {
                "dataset_id": "18717290",
                "extension": "bam",
                "file_size": 412673188,
                "name": "Cinex_CTTGTA_L001_R2_001",
                "param_name": "bamfiles22"
            },
            {
                "dataset_id": "18717444",
                "extension": "bam",
                "file_size": 333124443,
                "name": "DakiniKushMale_TAGCTT_L001",
                "param_name": "bamfiles23"
            },
            {
                "dataset_id": "18717450",
                "extension": "bam",
                "file_size": 230937645,
                "name": "DeepPurpleHaze_GGCTAC_L001",
                "param_name": "bamfiles24"
            },
            {
                "dataset_id": "18717461",
                "extension": "bam",
                "file_size": 230989463,
                "name": "DiamondGirl_AGTCAA_L001",
                "param_name": "bamfiles25"
            },
            {
                "dataset_id": "18717487",
                "extension": "bam",
                "file_size": 72286977,
                "name": "EastCoastSourDiesel_TTAGGC_L001",
                "param_name": "bamfiles26"
            },
            {
                "dataset_id": "18717737",
                "extension": "bam",
                "file_size": 2895695,
                "name": "FireOG_GATCAG_L001",
                "param_name": "bamfiles27"
            },
            {
                "dataset_id": "18717742",
                "extension": "bam",
                "file_size": 377475154,
                "name": "G4XSFMSCC_Pooled_L001",
                "param_name": "bamfiles28"
            },
            {
                "dataset_id": "18717747",
                "extension": "bam",
                "file_size": 207526487,
                "name": "GirlScoutCookie_CTTGTA_L001",
                "param_name": "bamfiles29"
            },
            {
                "dataset_id": "18717754",
                "extension": "bam",
                "file_size": 273873340,
                "name": "GrapeStomper_GATCAG_L001",
                "param_name": "bamfiles30"
            },
            {
                "dataset_id": "18717759",
                "extension": "bam",
                "file_size": 386567783,
                "name": "GreenCrackSCC_TGACCA_L001",
                "param_name": "bamfiles31"
            },
            {
                "dataset_id": "18720021",
                "extension": "bam",
                "file_size": 188403060,
                "name": "Haleys_CGATGT_L001",
                "param_name": "bamfiles32"
            },
            {
                "dataset_id": "18720028",
                "extension": "bam",
                "file_size": 205922558,
                "name": "JackHerer_CAGATC_L001",
                "param_name": "bamfiles33"
            },
            {
                "dataset_id": "18720034",
                "extension": "bam",
                "file_size": 4176707,
                "name": "JambaCity_ACTTGA_L001",
                "param_name": "bamfiles34"
            },
            {
                "dataset_id": "18720041",
                "extension": "bam",
                "file_size": 811722970,
                "name": "KushITSCC_TAGCTT_L001",
                "param_name": "bamfiles35"
            },
            {
                "dataset_id": "18720318",
                "extension": "bam",
                "file_size": 608359202,
                "name": "LuckyCharms_GGCTAC_L001",
                "param_name": "bamfiles36"
            },
            {
                "dataset_id": "18720333",
                "extension": "bam",
                "file_size": 494814527,
                "name": "MicheNepalMale_ACTTGA_L001",
                "param_name": "bamfiles37"
            },
            {
                "dataset_id": "18720343",
                "extension": "bam",
                "file_size": 403696525,
                "name": "MoonshineHaze2_ATCACG_L001",
                "param_name": "bamfiles38"
            },
            {
                "dataset_id": "18720350",
                "extension": "bam",
                "file_size": 325441153,
                "name": "OGKushSCC_ACAGTG_L001",
                "param_name": "bamfiles39"
            },
            {
                "dataset_id": "18720355",
                "extension": "bam",
                "file_size": 7943433,
                "name": "OGKushTest1_GCCAAT_L001",
                "param_name": "bamfiles40"
            },
            {
                "dataset_id": "18720423",
                "extension": "bam",
                "file_size": 228827430,
                "name": "OGKushXSFMSCC_Pooled_L001",
                "param_name": "bamfiles41"
            },
            {
                "dataset_id": "18720429",
                "extension": "bam",
                "file_size": 364896707,
                "name": "OGXPKSCC_Pooled_L001_R2_001",
                "param_name": "bamfiles42"
            },
            {
                "dataset_id": "18720443",
                "extension": "bam",
                "file_size": 360149974,
                "name": "PKX808OGSCC_Pooled_L001",
                "param_name": "bamfiles43"
            },
            {
                "dataset_id": "18720450",
                "extension": "bam",
                "file_size": 117527852,
                "name": "PureKush_GATCAG_L001",
                "param_name": "bamfiles44"
            },
            {
                "dataset_id": "18720555",
                "extension": "bam",
                "file_size": 701098590,
                "name": "RedDevil_TAGCTT_L001",
                "param_name": "bamfiles45"
            },
            {
                "dataset_id": "18720560",
                "extension": "bam",
                "file_size": 425766745,
                "name": "Ringo_ACAGTG_L001",
                "param_name": "bamfiles46"
            },
            {
                "dataset_id": "18720565",
                "extension": "bam",
                "file_size": 134868018,
                "name": "RioNegraMale_GGCTAC_L001",
                "param_name": "bamfiles47"
            },
            {
                "dataset_id": "18720570",
                "extension": "bam",
                "file_size": 294303338,
                "name": "RollexKush_ATCACG_L001",
                "param_name": "bamfiles48"
            },
            {
                "dataset_id": "18720575",
                "extension": "bam",
                "file_size": 619823415,
                "name": "SSHXWWSCC_Pooled_L001",
                "param_name": "bamfiles49"
            },
            {
                "dataset_id": "18721160",
                "extension": "bam",
                "file_size": 330162946,
                "name": "SecretOG_CAGATC_L001",
                "param_name": "bamfiles50"
            },
            {
                "dataset_id": "18721165",
                "extension": "bam",
                "file_size": 200630634,
                "name": "SensiStarXSFMSCC_Pooled_L001",
                "param_name": "bamfiles51"
            },
            {
                "dataset_id": "18721172",
                "extension": "bam",
                "file_size": 506833056,
                "name": "SnoopDream_GATCAG_L001",
                "param_name": "bamfiles52"
            },
            {
                "dataset_id": "18721177",
                "extension": "bam",
                "file_size": 410814551,
                "name": "SourTsunami_TAGCTT_L001",
                "param_name": "bamfiles53"
            },
            {
                "dataset_id": "18721183",
                "extension": "bam",
                "file_size": 230063731,
                "name": "SuperLemonHaze_ACAGTG_L001",
                "param_name": "bamfiles54"
            },
            {
                "dataset_id": "18721188",
                "extension": "bam",
                "file_size": 332297773,
                "name": "TrainwreckSCC_CGATGT_L001",
                "param_name": "bamfiles55"
            },
            {
                "dataset_id": "18721206",
                "extension": "bam",
                "file_size": 252882138,
                "name": "WIFIGTUBE_CGATGT_L001",
                "param_name": "bamfiles56"
            },
            {
                "dataset_id": "18721211",
                "extension": "bam",
                "file_size": 250960004,
                "name": "WIFI_ACTTGA_L001",
                "param_name": "bamfiles57"
            },
            {
                "dataset_id": "18721217",
                "extension": "bam",
                "file_size": 496783839,
                "name": "WZ_TGACCA_L001",
                "param_name": "bamfiles58"
            },
            {
                "dataset_id": "18721222",
                "extension": "bam",
                "file_size": 3337062,
                "name": "Watermelonhazemale_CTTGTA_L001",
                "param_name": "bamfiles59"
            },
            {
                "dataset_id": "18721239",
                "extension": "bam",
                "file_size": 567023717,
                "name": "WhiteWidow_CAGATC_L001",
                "param_name": "bamfiles60"
            },
            {
                "dataset_id": "18721245",
                "extension": "bam",
                "file_size": 428888220,
                "name": "WonderWoman_ACTTGA_L001",
                "param_name": "bamfiles61"
            },
            {
                "dataset_id": "18721252",
                "extension": "bam",
                "file_size": 273079350,
                "name": "YeddiMale_GATCAG_L001",
                "param_name": "bamfiles62"
            }
        ],
        "dependencies": [
            {
                "cacheable": true,
                "dependency_type": "conda",
                "environment_path": "/galaxy-repl/main/jobdir/014/975/14975222/conda-env",
                "exact": true,
                "model_class": "CondaDependency",
                "name": "python",
                "version": "2.7.10"
            },
            {
                "cacheable": true,
                "dependency_type": "conda",
                "environment_path": "/galaxy-repl/main/jobdir/014/975/14975222/conda-env",
                "exact": true,
                "model_class": "CondaDependency",
                "name": "deepTools",
                "version": "2.3.6"
            }
        ],
        "destination_id": "slurm_multi",
        "destination_params": {
            "nativeSpecification": "--time=36:00:00 --nodes=1 --ntasks=6 --partition=multi"
        },
        "exit_code": null,
        "handler": "main_w4_handler2",
        "history_id": 2981355,
        "id": 14975222,
        "imported": false,
        "info": "This job was terminated because it ran longer than the maximum allowed job run time.\nPlease click the bug icon to report this problem if you need help.",
        "job_runner_external_id": "9132858",
        "job_runner_name": "slurm",
        "library_folder_id": null,
        "metrics": {},
        "object_store_id": "corral-repl",
        "param_filename": null,
        "parameters": {
            "__job_resource": "{\"__current_case__\": 0, \"__job_resource__select\": \"no\"}",
            "advancedOpt": "{\"showAdvancedOpt\": \"no\", \"__current_case__\": 0}",
            "bamfiles": "{\"values\": [{\"src\": \"hda\", \"id\": 28208034}, {\"src\": \"hda\", \"id\": 28208145}, {\"src\": \"hda\", \"id\": 28208196}, {\"src\": \"hda\", \"id\": 28208442}, {\"src\": \"hda\", \"id\": 28208462}, {\"src\": \"hda\", \"id\": 28208526}, {\"src\": \"hda\", \"id\": 28208616}, {\"src\": \"hda\", \"id\": 28209597}, {\"src\": \"hda\", \"id\": 28209605}, {\"src\": \"hda\", \"id\": 28209659}, {\"src\": \"hda\", \"id\": 28209699}, {\"src\": \"hda\", \"id\": 28210472}, {\"src\": \"hda\", \"id\": 28210479}, {\"src\": \"hda\", \"id\": 28210511}, {\"src\": \"hda\", \"id\": 28210520}, {\"src\": \"hda\", \"id\": 28210540}, {\"src\": \"hda\", \"id\": 28210583}, {\"src\": \"hda\", \"id\": 28210590}, {\"src\": \"hda\", \"id\": 28211279}, {\"src\": \"hda\", \"id\": 28211288}, {\"src\": \"hda\", \"id\": 28211332}, {\"src\": \"hda\", \"id\": 28211343}, {\"src\": \"hda\", \"id\": 28211505}, {\"src\": \"hda\", \"id\": 28211511}, {\"src\": \"hda\", \"id\": 28211522}, {\"src\": \"hda\", \"id\": 28211548}, {\"src\": \"hda\", \"id\": 28211804}, {\"src\": \"hda\", \"id\": 28211809}, {\"src\": \"hda\", \"id\": 28211814}, {\"src\": \"hda\", \"id\": 28211821}, {\"src\": \"hda\", \"id\": 28211826}, {\"src\": \"hda\", \"id\": 28214993}, {\"src\": \"hda\", \"id\": 28215000}, {\"src\": \"hda\", \"id\": 28215006}, {\"src\": \"hda\", \"id\": 28215013}, {\"src\": \"hda\", \"id\": 28215308}, {\"src\": \"hda\", \"id\": 28215323}, {\"src\": \"hda\", \"id\": 28215333}, {\"src\": \"hda\", \"id\": 28215340}, {\"src\": \"hda\", \"id\": 28215345}, {\"src\": \"hda\", \"id\": 28215413}, {\"src\": \"hda\", \"id\": 28215419}, {\"src\": \"hda\", \"id\": 28215433}, {\"src\": \"hda\", \"id\": 28215440}, {\"src\": \"hda\", \"id\": 28215547}, {\"src\": \"hda\", \"id\": 28215552}, {\"src\": \"hda\", \"id\": 28215557}, {\"src\": \"hda\", \"id\": 28215562}, {\"src\": \"hda\", \"id\": 28215567}, {\"src\": \"hda\", \"id\": 28216168}, {\"src\": \"hda\", \"id\": 28216173}, {\"src\": \"hda\", \"id\": 28216180}, {\"src\": \"hda\", \"id\": 28216185}, {\"src\": \"hda\", \"id\": 28216191}, {\"src\": \"hda\", \"id\": 28216196}, {\"src\": \"hda\", \"id\": 28216214}, {\"src\": \"hda\", \"id\": 28216219}, {\"src\": \"hda\", \"id\": 28216225}, {\"src\": \"hda\", \"id\": 28216230}, {\"src\": \"hda\", \"id\": 28216247}, {\"src\": \"hda\", \"id\": 28216253}, {\"src\": \"hda\", \"id\": 28216261}]}",
            "chromInfo": "\"/galaxy-repl/main/files/012/373/dataset_12373292.dat\"",
            "dbkey": "\"canSat3\"",
            "mode": "{\"binSize\": \"10000\", \"distanceBetweenBins\": \"0\", \"__current_case__\": 0, \"modeOpt\": \"bins\"}",
            "outRawCounts": "\"false\"",
            "region": "\"\""
        },
        "runner_name": null,
        "session_id": 35650227,
        "state": "error",
        "tool_id": "toolshed.g2.bx.psu.edu/repos/bgruening/deeptools_multi_bam_summary/deeptools_multi_bam_summary/2.3.6.0",
        "tool_version": "2.3.6.0",
        "traceback": null,
        "update_time": "2017-02-09 06:31:04.943119",
        "user_id": 21426
    },
    {
        "create_time": "2017-02-11 13:55:20.472639",
        "datasets": [
            {
                "dataset_id": "18714174",
                "extension": "bam",
                "file_size": 624723735,
                "name": "AK47_TGACCA_L001",
                "param_name": "bamfiles"
            },
            {
                "dataset_id": "18714174",
                "extension": "bam",
                "file_size": 624723735,
                "name": "AK47_TGACCA_L001",
                "param_name": "bamfiles1"
            },
            {
                "dataset_id": "18714282",
                "extension": "bam",
                "file_size": 613505804,
                "name": "AfghanKush_CGATGT_L001",
                "param_name": "bamfiles2"
            },
            {
                "dataset_id": "18714333",
                "extension": "bam",
                "file_size": 192940192,
                "name": "Afgooey_ACTTGA_L001",
                "param_name": "bamfiles3"
            },
            {
                "dataset_id": "18714564",
                "extension": "bam",
                "file_size": 489945762,
                "name": "AlaskanIce_TTAGGC_L001",
                "param_name": "bamfiles4"
            },
            {
                "dataset_id": "18714584",
                "extension": "bam",
                "file_size": 313137453,
                "name": "ArjanUltraHaze2_GCCAAT_L001",
                "param_name": "bamfiles5"
            },
            {
                "dataset_id": "18714646",
                "extension": "bam",
                "file_size": 243532641,
                "name": "AustralianBastard_TTAGGC_L001",
                "param_name": "bamfiles6"
            },
            {
                "dataset_id": "18714734",
                "extension": "bam",
                "file_size": 243532643,
                "name": "BlueBerryCheeseCake18_ACAGTG_L001",
                "param_name": "bamfiles7"
            },
            {
                "dataset_id": "18715697",
                "extension": "bam",
                "file_size": 413003853,
                "name": "BlueBerryCheeseCakeBC2Fem_TAGCTT_L001",
                "param_name": "bamfiles8"
            },
            {
                "dataset_id": "18715705",
                "extension": "bam",
                "file_size": 414003695,
                "name": "BlueBerryEssense_CAGATC_L001",
                "param_name": "bamfiles9"
            },
            {
                "dataset_id": "18715759",
                "extension": "bam",
                "file_size": 334014135,
                "name": "BlueDreamSCC_CAGATC_L001",
                "param_name": "bamfiles10"
            },
            {
                "dataset_id": "18715798",
                "extension": "bam",
                "file_size": 692881481,
                "name": "Breakthrough_CTTGTA_L001",
                "param_name": "bamfiles11"
            },
            {
                "dataset_id": "18716513",
                "extension": "bam",
                "file_size": 275109667,
                "name": "C4XCanatsuSCC_Pooled_L001",
                "param_name": "bamfiles12"
            },
            {
                "dataset_id": "18716520",
                "extension": "bam",
                "file_size": 360911840,
                "name": "CBDMangoHaze_CAGATC_L001",
                "param_name": "bamfiles13"
            },
            {
                "dataset_id": "18716550",
                "extension": "bam",
                "file_size": 223969320,
                "name": "CanaTsuSCC_GATCAG_L001",
                "param_name": "bamfiles14"
            },
            {
                "dataset_id": "18716559",
                "extension": "bam",
                "file_size": 391115675,
                "name": "CaseyJones_ACAGTG_L001",
                "param_name": "bamfiles15"
            },
            {
                "dataset_id": "18716575",
                "extension": "bam",
                "file_size": 45295398,
                "name": "CheeseGHS_AGTTCC_L001",
                "param_name": "bamfiles16"
            },
            {
                "dataset_id": "18716618",
                "extension": "bam",
                "file_size": 29786038,
                "name": "ChemDawg91_GCCAAT_L001",
                "param_name": "bamfiles17"
            },
            {
                "dataset_id": "18716625",
                "extension": "bam",
                "file_size": 331182787,
                "name": "ChemDawg_ATCACG_L001",
                "param_name": "bamfiles18"
            },
            {
                "dataset_id": "18717240",
                "extension": "bam",
                "file_size": 557341204,
                "name": "ChemDog18cycles_ATCACG_L001",
                "param_name": "bamfiles19"
            },
            {
                "dataset_id": "18717249",
                "extension": "bam",
                "file_size": 379850451,
                "name": "ChemDog_TTAGGC_L001",
                "param_name": "bamfiles20"
            },
            {
                "dataset_id": "18717279",
                "extension": "bam",
                "file_size": 338227868,
                "name": "ChemdogXCherryPieSCC_TTAGGC_L001",
                "param_name": "bamfiles21"
            },
            {
                "dataset_id": "18717290",
                "extension": "bam",
                "file_size": 412673188,
                "name": "Cinex_CTTGTA_L001_R2_001",
                "param_name": "bamfiles22"
            },
            {
                "dataset_id": "18717444",
                "extension": "bam",
                "file_size": 333124443,
                "name": "DakiniKushMale_TAGCTT_L001",
                "param_name": "bamfiles23"
            },
            {
                "dataset_id": "18717450",
                "extension": "bam",
                "file_size": 230937645,
                "name": "DeepPurpleHaze_GGCTAC_L001",
                "param_name": "bamfiles24"
            },
            {
                "dataset_id": "18717461",
                "extension": "bam",
                "file_size": 230989463,
                "name": "DiamondGirl_AGTCAA_L001",
                "param_name": "bamfiles25"
            },
            {
                "dataset_id": "18717487",
                "extension": "bam",
                "file_size": 72286977,
                "name": "EastCoastSourDiesel_TTAGGC_L001",
                "param_name": "bamfiles26"
            },
            {
                "dataset_id": "18717737",
                "extension": "bam",
                "file_size": 2895695,
                "name": "FireOG_GATCAG_L001",
                "param_name": "bamfiles27"
            },
            {
                "dataset_id": "18717742",
                "extension": "bam",
                "file_size": 377475154,
                "name": "G4XSFMSCC_Pooled_L001",
                "param_name": "bamfiles28"
            },
            {
                "dataset_id": "18717747",
                "extension": "bam",
                "file_size": 207526487,
                "name": "GirlScoutCookie_CTTGTA_L001",
                "param_name": "bamfiles29"
            },
            {
                "dataset_id": "18717754",
                "extension": "bam",
                "file_size": 273873340,
                "name": "GrapeStomper_GATCAG_L001",
                "param_name": "bamfiles30"
            },
            {
                "dataset_id": "18717759",
                "extension": "bam",
                "file_size": 386567783,
                "name": "GreenCrackSCC_TGACCA_L001",
                "param_name": "bamfiles31"
            },
            {
                "dataset_id": "18720021",
                "extension": "bam",
                "file_size": 188403060,
                "name": "Haleys_CGATGT_L001",
                "param_name": "bamfiles32"
            },
            {
                "dataset_id": "18720028",
                "extension": "bam",
                "file_size": 205922558,
                "name": "JackHerer_CAGATC_L001",
                "param_name": "bamfiles33"
            },
            {
                "dataset_id": "18720034",
                "extension": "bam",
                "file_size": 4176707,
                "name": "JambaCity_ACTTGA_L001",
                "param_name": "bamfiles34"
            },
            {
                "dataset_id": "18720041",
                "extension": "bam",
                "file_size": 811722970,
                "name": "KushITSCC_TAGCTT_L001",
                "param_name": "bamfiles35"
            },
            {
                "dataset_id": "18720318",
                "extension": "bam",
                "file_size": 608359202,
                "name": "LuckyCharms_GGCTAC_L001",
                "param_name": "bamfiles36"
            },
            {
                "dataset_id": "18720333",
                "extension": "bam",
                "file_size": 494814527,
                "name": "MicheNepalMale_ACTTGA_L001",
                "param_name": "bamfiles37"
            },
            {
                "dataset_id": "18720343",
                "extension": "bam",
                "file_size": 403696525,
                "name": "MoonshineHaze2_ATCACG_L001",
                "param_name": "bamfiles38"
            },
            {
                "dataset_id": "18720350",
                "extension": "bam",
                "file_size": 325441153,
                "name": "OGKushSCC_ACAGTG_L001",
                "param_name": "bamfiles39"
            },
            {
                "dataset_id": "18720355",
                "extension": "bam",
                "file_size": 7943433,
                "name": "OGKushTest1_GCCAAT_L001",
                "param_name": "bamfiles40"
            },
            {
                "dataset_id": "18720423",
                "extension": "bam",
                "file_size": 228827430,
                "name": "OGKushXSFMSCC_Pooled_L001",
                "param_name": "bamfiles41"
            },
            {
                "dataset_id": "18720429",
                "extension": "bam",
                "file_size": 364896707,
                "name": "OGXPKSCC_Pooled_L001_R2_001",
                "param_name": "bamfiles42"
            },
            {
                "dataset_id": "18720443",
                "extension": "bam",
                "file_size": 360149974,
                "name": "PKX808OGSCC_Pooled_L001",
                "param_name": "bamfiles43"
            },
            {
                "dataset_id": "18720450",
                "extension": "bam",
                "file_size": 117527852,
                "name": "PureKush_GATCAG_L001",
                "param_name": "bamfiles44"
            },
            {
                "dataset_id": "18720555",
                "extension": "bam",
                "file_size": 701098590,
                "name": "RedDevil_TAGCTT_L001",
                "param_name": "bamfiles45"
            },
            {
                "dataset_id": "18720560",
                "extension": "bam",
                "file_size": 425766745,
                "name": "Ringo_ACAGTG_L001",
                "param_name": "bamfiles46"
            },
            {
                "dataset_id": "18720565",
                "extension": "bam",
                "file_size": 134868018,
                "name": "RioNegraMale_GGCTAC_L001",
                "param_name": "bamfiles47"
            },
            {
                "dataset_id": "18720570",
                "extension": "bam",
                "file_size": 294303338,
                "name": "RollexKush_ATCACG_L001",
                "param_name": "bamfiles48"
            },
            {
                "dataset_id": "18720575",
                "extension": "bam",
                "file_size": 619823415,
                "name": "SSHXWWSCC_Pooled_L001",
                "param_name": "bamfiles49"
            },
            {
                "dataset_id": "18721160",
                "extension": "bam",
                "file_size": 330162946,
                "name": "SecretOG_CAGATC_L001",
                "param_name": "bamfiles50"
            },
            {
                "dataset_id": "18721165",
                "extension": "bam",
                "file_size": 200630634,
                "name": "SensiStarXSFMSCC_Pooled_L001",
                "param_name": "bamfiles51"
            },
            {
                "dataset_id": "18721172",
                "extension": "bam",
                "file_size": 506833056,
                "name": "SnoopDream_GATCAG_L001",
                "param_name": "bamfiles52"
            },
            {
                "dataset_id": "18721177",
                "extension": "bam",
                "file_size": 410814551,
                "name": "SourTsunami_TAGCTT_L001",
                "param_name": "bamfiles53"
            },
            {
                "dataset_id": "18721183",
                "extension": "bam",
                "file_size": 230063731,
                "name": "SuperLemonHaze_ACAGTG_L001",
                "param_name": "bamfiles54"
            },
            {
                "dataset_id": "18721188",
                "extension": "bam",
                "file_size": 332297773,
                "name": "TrainwreckSCC_CGATGT_L001",
                "param_name": "bamfiles55"
            },
            {
                "dataset_id": "18721206",
                "extension": "bam",
                "file_size": 252882138,
                "name": "WIFIGTUBE_CGATGT_L001",
                "param_name": "bamfiles56"
            },
            {
                "dataset_id": "18721211",
                "extension": "bam",
                "file_size": 250960004,
                "name": "WIFI_ACTTGA_L001",
                "param_name": "bamfiles57"
            },
            {
                "dataset_id": "18721217",
                "extension": "bam",
                "file_size": 496783839,
                "name": "WZ_TGACCA_L001",
                "param_name": "bamfiles58"
            },
            {
                "dataset_id": "18721222",
                "extension": "bam",
                "file_size": 3337062,
                "name": "Watermelonhazemale_CTTGTA_L001",
                "param_name": "bamfiles59"
            },
            {
                "dataset_id": "18721239",
                "extension": "bam",
                "file_size": 567023717,
                "name": "WhiteWidow_CAGATC_L001",
                "param_name": "bamfiles60"
            },
            {
                "dataset_id": "18721245",
                "extension": "bam",
                "file_size": 428888220,
                "name": "WonderWoman_ACTTGA_L001",
                "param_name": "bamfiles61"
            },
            {
                "dataset_id": "18721252",
                "extension": "bam",
                "file_size": 273079350,
                "name": "YeddiMale_GATCAG_L001",
                "param_name": "bamfiles62"
            }
        ],
        "dependencies": [
            {
                "cacheable": true,
                "dependency_type": "conda",
                "environment_path": "/galaxy-repl/main/jobdir/015/011/15011199/conda-env",
                "exact": true,
                "model_class": "CondaDependency",
                "name": "python",
                "version": "2.7.10"
            },
            {
                "cacheable": true,
                "dependency_type": "conda",
                "environment_path": "/galaxy-repl/main/jobdir/015/011/15011199/conda-env",
                "exact": true,
                "model_class": "CondaDependency",
                "name": "deepTools",
                "version": "2.3.6"
            }
        ],
        "destination_id": "slurm_multi",
        "destination_params": {
            "nativeSpecification": "--time=36:00:00 --nodes=1 --ntasks=6 --partition=multi"
        },
        "exit_code": null,
        "handler": "main_w4_handler2",
        "history_id": 2981355,
        "id": 15011199,
        "imported": false,
        "info": "This job was terminated because it ran longer than the maximum allowed job run time.\nPlease click the bug icon to report this problem if you need help.",
        "job_runner_external_id": "9167490",
        "job_runner_name": "slurm",
        "library_folder_id": null,
        "metrics": {},
        "object_store_id": "corral-repl",
        "param_filename": null,
        "parameters": {
            "__job_resource": "{\"__current_case__\": 0, \"__job_resource__select\": \"no\"}",
            "advancedOpt": "{\"showAdvancedOpt\": \"no\", \"__current_case__\": 0}",
            "bamfiles": "{\"values\": [{\"src\": \"hda\", \"id\": 28208034}, {\"src\": \"hda\", \"id\": 28208145}, {\"src\": \"hda\", \"id\": 28208196}, {\"src\": \"hda\", \"id\": 28208442}, {\"src\": \"hda\", \"id\": 28208462}, {\"src\": \"hda\", \"id\": 28208526}, {\"src\": \"hda\", \"id\": 28208616}, {\"src\": \"hda\", \"id\": 28209597}, {\"src\": \"hda\", \"id\": 28209605}, {\"src\": \"hda\", \"id\": 28209659}, {\"src\": \"hda\", \"id\": 28209699}, {\"src\": \"hda\", \"id\": 28210472}, {\"src\": \"hda\", \"id\": 28210479}, {\"src\": \"hda\", \"id\": 28210511}, {\"src\": \"hda\", \"id\": 28210520}, {\"src\": \"hda\", \"id\": 28210540}, {\"src\": \"hda\", \"id\": 28210583}, {\"src\": \"hda\", \"id\": 28210590}, {\"src\": \"hda\", \"id\": 28211279}, {\"src\": \"hda\", \"id\": 28211288}, {\"src\": \"hda\", \"id\": 28211332}, {\"src\": \"hda\", \"id\": 28211343}, {\"src\": \"hda\", \"id\": 28211505}, {\"src\": \"hda\", \"id\": 28211511}, {\"src\": \"hda\", \"id\": 28211522}, {\"src\": \"hda\", \"id\": 28211548}, {\"src\": \"hda\", \"id\": 28211804}, {\"src\": \"hda\", \"id\": 28211809}, {\"src\": \"hda\", \"id\": 28211814}, {\"src\": \"hda\", \"id\": 28211821}, {\"src\": \"hda\", \"id\": 28211826}, {\"src\": \"hda\", \"id\": 28214993}, {\"src\": \"hda\", \"id\": 28215000}, {\"src\": \"hda\", \"id\": 28215006}, {\"src\": \"hda\", \"id\": 28215013}, {\"src\": \"hda\", \"id\": 28215308}, {\"src\": \"hda\", \"id\": 28215323}, {\"src\": \"hda\", \"id\": 28215333}, {\"src\": \"hda\", \"id\": 28215340}, {\"src\": \"hda\", \"id\": 28215345}, {\"src\": \"hda\", \"id\": 28215413}, {\"src\": \"hda\", \"id\": 28215419}, {\"src\": \"hda\", \"id\": 28215433}, {\"src\": \"hda\", \"id\": 28215440}, {\"src\": \"hda\", \"id\": 28215547}, {\"src\": \"hda\", \"id\": 28215552}, {\"src\": \"hda\", \"id\": 28215557}, {\"src\": \"hda\", \"id\": 28215562}, {\"src\": \"hda\", \"id\": 28215567}, {\"src\": \"hda\", \"id\": 28216168}, {\"src\": \"hda\", \"id\": 28216173}, {\"src\": \"hda\", \"id\": 28216180}, {\"src\": \"hda\", \"id\": 28216185}, {\"src\": \"hda\", \"id\": 28216191}, {\"src\": \"hda\", \"id\": 28216196}, {\"src\": \"hda\", \"id\": 28216214}, {\"src\": \"hda\", \"id\": 28216219}, {\"src\": \"hda\", \"id\": 28216225}, {\"src\": \"hda\", \"id\": 28216230}, {\"src\": \"hda\", \"id\": 28216247}, {\"src\": \"hda\", \"id\": 28216253}, {\"src\": \"hda\", \"id\": 28216261}]}",
            "chromInfo": "\"/galaxy-repl/main/files/012/373/dataset_12373292.dat\"",
            "dbkey": "\"canSat3\"",
            "mode": "{\"binSize\": \"10000\", \"distanceBetweenBins\": \"0\", \"__current_case__\": 0, \"modeOpt\": \"bins\"}",
            "outRawCounts": "\"false\"",
            "region": "\"\""
        },
        "runner_name": null,
        "session_id": 35312913,
        "state": "error",
        "tool_id": "toolshed.g2.bx.psu.edu/repos/bgruening/deeptools_multi_bam_summary/deeptools_multi_bam_summary/2.3.6.0",
        "tool_version": "2.3.6.0",
        "traceback": null,
        "update_time": "2017-02-14 03:48:42.396239",
        "user_id": 21426
    },
    {
        "create_time": "2017-02-15 07:15:21.577424",
        "datasets": [
            {
                "dataset_id": "18714174",
                "extension": "bam",
                "file_size": 624723735,
                "name": "AK47_TGACCA_L001",
                "param_name": "bamfiles"
            },
            {
                "dataset_id": "18714174",
                "extension": "bam",
                "file_size": 624723735,
                "name": "AK47_TGACCA_L001",
                "param_name": "bamfiles1"
            },
            {
                "dataset_id": "18714282",
                "extension": "bam",
                "file_size": 613505804,
                "name": "AfghanKush_CGATGT_L001",
                "param_name": "bamfiles2"
            },
            {
                "dataset_id": "18714333",
                "extension": "bam",
                "file_size": 192940192,
                "name": "Afgooey_ACTTGA_L001",
                "param_name": "bamfiles3"
            },
            {
                "dataset_id": "18714564",
                "extension": "bam",
                "file_size": 489945762,
                "name": "AlaskanIce_TTAGGC_L001",
                "param_name": "bamfiles4"
            },
            {
                "dataset_id": "18714584",
                "extension": "bam",
                "file_size": 313137453,
                "name": "ArjanUltraHaze2_GCCAAT_L001",
                "param_name": "bamfiles5"
            },
            {
                "dataset_id": "18714646",
                "extension": "bam",
                "file_size": 243532641,
                "name": "AustralianBastard_TTAGGC_L001",
                "param_name": "bamfiles6"
            },
            {
                "dataset_id": "18714734",
                "extension": "bam",
                "file_size": 243532643,
                "name": "BlueBerryCheeseCake18_ACAGTG_L001",
                "param_name": "bamfiles7"
            },
            {
                "dataset_id": "18715697",
                "extension": "bam",
                "file_size": 413003853,
                "name": "BlueBerryCheeseCakeBC2Fem_TAGCTT_L001",
                "param_name": "bamfiles8"
            },
            {
                "dataset_id": "18715705",
                "extension": "bam",
                "file_size": 414003695,
                "name": "BlueBerryEssense_CAGATC_L001",
                "param_name": "bamfiles9"
            },
            {
                "dataset_id": "18715759",
                "extension": "bam",
                "file_size": 334014135,
                "name": "BlueDreamSCC_CAGATC_L001",
                "param_name": "bamfiles10"
            },
            {
                "dataset_id": "18715798",
                "extension": "bam",
                "file_size": 692881481,
                "name": "Breakthrough_CTTGTA_L001",
                "param_name": "bamfiles11"
            },
            {
                "dataset_id": "18716513",
                "extension": "bam",
                "file_size": 275109667,
                "name": "C4XCanatsuSCC_Pooled_L001",
                "param_name": "bamfiles12"
            },
            {
                "dataset_id": "18716520",
                "extension": "bam",
                "file_size": 360911840,
                "name": "CBDMangoHaze_CAGATC_L001",
                "param_name": "bamfiles13"
            },
            {
                "dataset_id": "18716550",
                "extension": "bam",
                "file_size": 223969320,
                "name": "CanaTsuSCC_GATCAG_L001",
                "param_name": "bamfiles14"
            },
            {
                "dataset_id": "18716559",
                "extension": "bam",
                "file_size": 391115675,
                "name": "CaseyJones_ACAGTG_L001",
                "param_name": "bamfiles15"
            },
            {
                "dataset_id": "18716575",
                "extension": "bam",
                "file_size": 45295398,
                "name": "CheeseGHS_AGTTCC_L001",
                "param_name": "bamfiles16"
            },
            {
                "dataset_id": "18716618",
                "extension": "bam",
                "file_size": 29786038,
                "name": "ChemDawg91_GCCAAT_L001",
                "param_name": "bamfiles17"
            },
            {
                "dataset_id": "18716625",
                "extension": "bam",
                "file_size": 331182787,
                "name": "ChemDawg_ATCACG_L001",
                "param_name": "bamfiles18"
            },
            {
                "dataset_id": "18717240",
                "extension": "bam",
                "file_size": 557341204,
                "name": "ChemDog18cycles_ATCACG_L001",
                "param_name": "bamfiles19"
            },
            {
                "dataset_id": "18717249",
                "extension": "bam",
                "file_size": 379850451,
                "name": "ChemDog_TTAGGC_L001",
                "param_name": "bamfiles20"
            },
            {
                "dataset_id": "18717279",
                "extension": "bam",
                "file_size": 338227868,
                "name": "ChemdogXCherryPieSCC_TTAGGC_L001",
                "param_name": "bamfiles21"
            },
            {
                "dataset_id": "18717290",
                "extension": "bam",
                "file_size": 412673188,
                "name": "Cinex_CTTGTA_L001_R2_001",
                "param_name": "bamfiles22"
            },
            {
                "dataset_id": "18717444",
                "extension": "bam",
                "file_size": 333124443,
                "name": "DakiniKushMale_TAGCTT_L001",
                "param_name": "bamfiles23"
            },
            {
                "dataset_id": "18717450",
                "extension": "bam",
                "file_size": 230937645,
                "name": "DeepPurpleHaze_GGCTAC_L001",
                "param_name": "bamfiles24"
            },
            {
                "dataset_id": "18717461",
                "extension": "bam",
                "file_size": 230989463,
                "name": "DiamondGirl_AGTCAA_L001",
                "param_name": "bamfiles25"
            },
            {
                "dataset_id": "18717487",
                "extension": "bam",
                "file_size": 72286977,
                "name": "EastCoastSourDiesel_TTAGGC_L001",
                "param_name": "bamfiles26"
            },
            {
                "dataset_id": "18717737",
                "extension": "bam",
                "file_size": 2895695,
                "name": "FireOG_GATCAG_L001",
                "param_name": "bamfiles27"
            },
            {
                "dataset_id": "18717742",
                "extension": "bam",
                "file_size": 377475154,
                "name": "G4XSFMSCC_Pooled_L001",
                "param_name": "bamfiles28"
            },
            {
                "dataset_id": "18717747",
                "extension": "bam",
                "file_size": 207526487,
                "name": "GirlScoutCookie_CTTGTA_L001",
                "param_name": "bamfiles29"
            },
            {
                "dataset_id": "18717754",
                "extension": "bam",
                "file_size": 273873340,
                "name": "GrapeStomper_GATCAG_L001",
                "param_name": "bamfiles30"
            },
            {
                "dataset_id": "18717759",
                "extension": "bam",
                "file_size": 386567783,
                "name": "GreenCrackSCC_TGACCA_L001",
                "param_name": "bamfiles31"
            },
            {
                "dataset_id": "18720021",
                "extension": "bam",
                "file_size": 188403060,
                "name": "Haleys_CGATGT_L001",
                "param_name": "bamfiles32"
            },
            {
                "dataset_id": "18720028",
                "extension": "bam",
                "file_size": 205922558,
                "name": "JackHerer_CAGATC_L001",
                "param_name": "bamfiles33"
            },
            {
                "dataset_id": "18720034",
                "extension": "bam",
                "file_size": 4176707,
                "name": "JambaCity_ACTTGA_L001",
                "param_name": "bamfiles34"
            },
            {
                "dataset_id": "18720041",
                "extension": "bam",
                "file_size": 811722970,
                "name": "KushITSCC_TAGCTT_L001",
                "param_name": "bamfiles35"
            },
            {
                "dataset_id": "18720318",
                "extension": "bam",
                "file_size": 608359202,
                "name": "LuckyCharms_GGCTAC_L001",
                "param_name": "bamfiles36"
            },
            {
                "dataset_id": "18720333",
                "extension": "bam",
                "file_size": 494814527,
                "name": "MicheNepalMale_ACTTGA_L001",
                "param_name": "bamfiles37"
            },
            {
                "dataset_id": "18720343",
                "extension": "bam",
                "file_size": 403696525,
                "name": "MoonshineHaze2_ATCACG_L001",
                "param_name": "bamfiles38"
            },
            {
                "dataset_id": "18720350",
                "extension": "bam",
                "file_size": 325441153,
                "name": "OGKushSCC_ACAGTG_L001",
                "param_name": "bamfiles39"
            },
            {
                "dataset_id": "18720355",
                "extension": "bam",
                "file_size": 7943433,
                "name": "OGKushTest1_GCCAAT_L001",
                "param_name": "bamfiles40"
            },
            {
                "dataset_id": "18720423",
                "extension": "bam",
                "file_size": 228827430,
                "name": "OGKushXSFMSCC_Pooled_L001",
                "param_name": "bamfiles41"
            },
            {
                "dataset_id": "18720429",
                "extension": "bam",
                "file_size": 364896707,
                "name": "OGXPKSCC_Pooled_L001_R2_001",
                "param_name": "bamfiles42"
            },
            {
                "dataset_id": "18720443",
                "extension": "bam",
                "file_size": 360149974,
                "name": "PKX808OGSCC_Pooled_L001",
                "param_name": "bamfiles43"
            },
            {
                "dataset_id": "18720450",
                "extension": "bam",
                "file_size": 117527852,
                "name": "PureKush_GATCAG_L001",
                "param_name": "bamfiles44"
            },
            {
                "dataset_id": "18720555",
                "extension": "bam",
                "file_size": 701098590,
                "name": "RedDevil_TAGCTT_L001",
                "param_name": "bamfiles45"
            },
            {
                "dataset_id": "18720560",
                "extension": "bam",
                "file_size": 425766745,
                "name": "Ringo_ACAGTG_L001",
                "param_name": "bamfiles46"
            },
            {
                "dataset_id": "18720565",
                "extension": "bam",
                "file_size": 134868018,
                "name": "RioNegraMale_GGCTAC_L001",
                "param_name": "bamfiles47"
            },
            {
                "dataset_id": "18720570",
                "extension": "bam",
                "file_size": 294303338,
                "name": "RollexKush_ATCACG_L001",
                "param_name": "bamfiles48"
            },
            {
                "dataset_id": "18720575",
                "extension": "bam",
                "file_size": 619823415,
                "name": "SSHXWWSCC_Pooled_L001",
                "param_name": "bamfiles49"
            },
            {
                "dataset_id": "18721160",
                "extension": "bam",
                "file_size": 330162946,
                "name": "SecretOG_CAGATC_L001",
                "param_name": "bamfiles50"
            },
            {
                "dataset_id": "18721165",
                "extension": "bam",
                "file_size": 200630634,
                "name": "SensiStarXSFMSCC_Pooled_L001",
                "param_name": "bamfiles51"
            },
            {
                "dataset_id": "18721172",
                "extension": "bam",
                "file_size": 506833056,
                "name": "SnoopDream_GATCAG_L001",
                "param_name": "bamfiles52"
            },
            {
                "dataset_id": "18721177",
                "extension": "bam",
                "file_size": 410814551,
                "name": "SourTsunami_TAGCTT_L001",
                "param_name": "bamfiles53"
            },
            {
                "dataset_id": "18721183",
                "extension": "bam",
                "file_size": 230063731,
                "name": "SuperLemonHaze_ACAGTG_L001",
                "param_name": "bamfiles54"
            },
            {
                "dataset_id": "18721188",
                "extension": "bam",
                "file_size": 332297773,
                "name": "TrainwreckSCC_CGATGT_L001",
                "param_name": "bamfiles55"
            },
            {
                "dataset_id": "18721206",
                "extension": "bam",
                "file_size": 252882138,
                "name": "WIFIGTUBE_CGATGT_L001",
                "param_name": "bamfiles56"
            },
            {
                "dataset_id": "18721211",
                "extension": "bam",
                "file_size": 250960004,
                "name": "WIFI_ACTTGA_L001",
                "param_name": "bamfiles57"
            },
            {
                "dataset_id": "18721217",
                "extension": "bam",
                "file_size": 496783839,
                "name": "WZ_TGACCA_L001",
                "param_name": "bamfiles58"
            },
            {
                "dataset_id": "18721222",
                "extension": "bam",
                "file_size": 3337062,
                "name": "Watermelonhazemale_CTTGTA_L001",
                "param_name": "bamfiles59"
            },
            {
                "dataset_id": "18721239",
                "extension": "bam",
                "file_size": 567023717,
                "name": "WhiteWidow_CAGATC_L001",
                "param_name": "bamfiles60"
            },
            {
                "dataset_id": "18721245",
                "extension": "bam",
                "file_size": 428888220,
                "name": "WonderWoman_ACTTGA_L001",
                "param_name": "bamfiles61"
            },
            {
                "dataset_id": "18721252",
                "extension": "bam",
                "file_size": 273079350,
                "name": "YeddiMale_GATCAG_L001",
                "param_name": "bamfiles62"
            }
        ],
        "dependencies": [
            {
                "cacheable": true,
                "dependency_type": "conda",
                "environment_path": "/galaxy-repl/main/jobdir/015/042/15042693/conda-env",
                "exact": true,
                "model_class": "CondaDependency",
                "name": "python",
                "version": "2.7.10"
            },
            {
                "cacheable": true,
                "dependency_type": "conda",
                "environment_path": "/galaxy-repl/main/jobdir/015/042/15042693/conda-env",
                "exact": true,
                "model_class": "CondaDependency",
                "name": "deepTools",
                "version": "2.3.6"
            }
        ],
        "destination_id": "slurm_multi",
        "destination_params": {
            "nativeSpecification": "--time=36:00:00 --nodes=1 --ntasks=6 --partition=multi"
        },
        "exit_code": null,
        "handler": "main_w4_handler2",
        "history_id": 2981355,
        "id": 15042693,
        "imported": false,
        "info": "This job was terminated because it ran longer than the maximum allowed job run time.\nPlease click the bug icon to report this problem if you need help.",
        "job_runner_external_id": "9198468",
        "job_runner_name": "slurm",
        "library_folder_id": null,
        "metrics": {},
        "object_store_id": "corral-repl",
        "param_filename": null,
        "parameters": {
            "__job_resource": "{\"__current_case__\": 0, \"__job_resource__select\": \"no\"}",
            "advancedOpt": "{\"showAdvancedOpt\": \"no\", \"__current_case__\": 0}",
            "bamfiles": "{\"values\": [{\"src\": \"hda\", \"id\": 28208034}, {\"src\": \"hda\", \"id\": 28208145}, {\"src\": \"hda\", \"id\": 28208196}, {\"src\": \"hda\", \"id\": 28208442}, {\"src\": \"hda\", \"id\": 28208462}, {\"src\": \"hda\", \"id\": 28208526}, {\"src\": \"hda\", \"id\": 28208616}, {\"src\": \"hda\", \"id\": 28209597}, {\"src\": \"hda\", \"id\": 28209605}, {\"src\": \"hda\", \"id\": 28209659}, {\"src\": \"hda\", \"id\": 28209699}, {\"src\": \"hda\", \"id\": 28210472}, {\"src\": \"hda\", \"id\": 28210479}, {\"src\": \"hda\", \"id\": 28210511}, {\"src\": \"hda\", \"id\": 28210520}, {\"src\": \"hda\", \"id\": 28210540}, {\"src\": \"hda\", \"id\": 28210583}, {\"src\": \"hda\", \"id\": 28210590}, {\"src\": \"hda\", \"id\": 28211279}, {\"src\": \"hda\", \"id\": 28211288}, {\"src\": \"hda\", \"id\": 28211332}, {\"src\": \"hda\", \"id\": 28211343}, {\"src\": \"hda\", \"id\": 28211505}, {\"src\": \"hda\", \"id\": 28211511}, {\"src\": \"hda\", \"id\": 28211522}, {\"src\": \"hda\", \"id\": 28211548}, {\"src\": \"hda\", \"id\": 28211804}, {\"src\": \"hda\", \"id\": 28211809}, {\"src\": \"hda\", \"id\": 28211814}, {\"src\": \"hda\", \"id\": 28211821}, {\"src\": \"hda\", \"id\": 28211826}, {\"src\": \"hda\", \"id\": 28214993}, {\"src\": \"hda\", \"id\": 28215000}, {\"src\": \"hda\", \"id\": 28215006}, {\"src\": \"hda\", \"id\": 28215013}, {\"src\": \"hda\", \"id\": 28215308}, {\"src\": \"hda\", \"id\": 28215323}, {\"src\": \"hda\", \"id\": 28215333}, {\"src\": \"hda\", \"id\": 28215340}, {\"src\": \"hda\", \"id\": 28215345}, {\"src\": \"hda\", \"id\": 28215413}, {\"src\": \"hda\", \"id\": 28215419}, {\"src\": \"hda\", \"id\": 28215433}, {\"src\": \"hda\", \"id\": 28215440}, {\"src\": \"hda\", \"id\": 28215547}, {\"src\": \"hda\", \"id\": 28215552}, {\"src\": \"hda\", \"id\": 28215557}, {\"src\": \"hda\", \"id\": 28215562}, {\"src\": \"hda\", \"id\": 28215567}, {\"src\": \"hda\", \"id\": 28216168}, {\"src\": \"hda\", \"id\": 28216173}, {\"src\": \"hda\", \"id\": 28216180}, {\"src\": \"hda\", \"id\": 28216185}, {\"src\": \"hda\", \"id\": 28216191}, {\"src\": \"hda\", \"id\": 28216196}, {\"src\": \"hda\", \"id\": 28216214}, {\"src\": \"hda\", \"id\": 28216219}, {\"src\": \"hda\", \"id\": 28216225}, {\"src\": \"hda\", \"id\": 28216230}, {\"src\": \"hda\", \"id\": 28216247}, {\"src\": \"hda\", \"id\": 28216253}, {\"src\": \"hda\", \"id\": 28216261}]}",
            "chromInfo": "\"/galaxy-repl/main/files/012/373/dataset_12373292.dat\"",
            "dbkey": "\"canSat3\"",
            "mode": "{\"binSize\": \"50000\", \"distanceBetweenBins\": \"0\", \"__current_case__\": 0, \"modeOpt\": \"bins\"}",
            "outRawCounts": "\"false\"",
            "region": "\"\""
        },
        "runner_name": null,
        "session_id": 35650227,
        "state": "error",
        "tool_id": "toolshed.g2.bx.psu.edu/repos/bgruening/deeptools_multi_bam_summary/deeptools_multi_bam_summary/2.3.6.0",
        "tool_version": "2.3.6.0",
        "traceback": null,
        "update_time": "2017-02-16 19:17:47.330432",
        "user_id": 21426
    }
]