[
    {
        "create_time": "2017-08-31 13:42:05.749057",
        "datasets": [
            {
                "dataset_id": "21110896",
                "extension": "gtf",
                "file_size": 307342249,
                "name": "Cufflinks on data 455 and data 473: assembled transcripts",
                "param_name": "input_tabular"
            },
            {
                "dataset_id": "21110896",
                "extension": "gtf",
                "file_size": 307342249,
                "name": "Cufflinks on data 455 and data 473: assembled transcripts",
                "param_name": "input_tabular1"
            },
            {
                "dataset_id": "21110901",
                "extension": "gtf",
                "file_size": 307465298,
                "name": "Cufflinks on data 455 and data 477: assembled transcripts",
                "param_name": "input_tabular2"
            },
            {
                "dataset_id": "21110906",
                "extension": "gtf",
                "file_size": 307401928,
                "name": "Cufflinks on data 455 and data 481: assembled transcripts",
                "param_name": "input_tabular3"
            },
            {
                "dataset_id": "21110912",
                "extension": "gtf",
                "file_size": 307501495,
                "name": "Cufflinks on data 455 and data 485: assembled transcripts",
                "param_name": "input_tabular4"
            },
            {
                "dataset_id": "21110917",
                "extension": "gtf",
                "file_size": 307611009,
                "name": "Cufflinks on data 455 and data 489: assembled transcripts",
                "param_name": "input_tabular5"
            },
            {
                "dataset_id": "21110922",
                "extension": "gtf",
                "file_size": 307524086,
                "name": "Cufflinks on data 455 and data 493: assembled transcripts",
                "param_name": "input_tabular6"
            },
            {
                "dataset_id": "21110927",
                "extension": "gtf",
                "file_size": 307661481,
                "name": "Cufflinks on data 455 and data 497: assembled transcripts",
                "param_name": "input_tabular7"
            },
            {
                "dataset_id": "21110932",
                "extension": "gtf",
                "file_size": 307610429,
                "name": "Cufflinks on data 455 and data 501: assembled transcripts",
                "param_name": "input_tabular8"
            }
        ],
        "dependencies": [
            {
                "cacheable": false,
                "dependency_type": "tool_shed_package",
                "exact": true,
                "model_class": "ToolShedDependency",
                "name": "gnu_coreutils",
                "path": "/galaxy/main/deps/gnu_coreutils/8.22/iuc/collection_column_join/9c8536c7ed42",
                "script": "/galaxy/main/deps/gnu_coreutils/8.22/iuc/collection_column_join/9c8536c7ed42/env.sh",
                "version": "8.22"
            }
        ],
        "destination_id": "slurm_normal",
        "destination_params": {
            "nativeSpecification": "--time=36:00:00 --clusters=roundup --nodes=1 --ntasks=1 --partition=normal"
        },
        "exit_code": null,
        "handler": "main_w4_handler0",
        "history_id": 3217414,
        "id": 16702982,
        "imported": false,
        "info": "This job was terminated because it ran longer than the maximum allowed job run time.\nPlease click the bug icon to report this problem if you need help.",
        "job_runner_external_id": "10775591.roundup",
        "job_runner_name": "slurm",
        "library_folder_id": null,
        "metrics": {},
        "object_store_id": "corral-repl",
        "param_filename": null,
        "parameters": {
            "chromInfo": "\"/galaxy-repl/localdata/chrom/?.len\"",
            "dbkey": "\"?\"",
            "fill_char": "\".\"",
            "has_header": "\"0\"",
            "identifier_column": "\"1\"",
            "include_outputs": "null",
            "input_tabular": "{\"values\": [{\"src\": \"hda\", \"id\": 31044306}, {\"src\": \"hda\", \"id\": 31044311}, {\"src\": \"hda\", \"id\": 31044316}, {\"src\": \"hda\", \"id\": 31044322}, {\"src\": \"hda\", \"id\": 31044327}, {\"src\": \"hda\", \"id\": 31044332}, {\"src\": \"hda\", \"id\": 31044337}, {\"src\": \"hda\", \"id\": 31044342}]}"
        },
        "runner_name": null,
        "session_id": 39874217,
        "state": "error",
        "tool_id": "toolshed.g2.bx.psu.edu/repos/iuc/collection_column_join/collection_column_join/0.0.1",
        "tool_version": "0.0.1",
        "traceback": null,
        "update_time": "2017-09-02 01:43:06.317104",
        "user_id": 109973
    }
]